{
    "name": "Global Information",
    "numberOfRequests": {
        "total": 13,
        "ok": 13,
        "ko": 0
    },
    "minResponseTime": {
        "total": 148,
        "ok": 148,
        "ko": 0
    },
    "maxResponseTime": {
        "total": 354,
        "ok": 354,
        "ko": 0
    },
    "meanResponseTime": {
        "total": 170,
        "ok": 170,
        "ko": 0
    },
    "standardDeviation": {
        "total": 54,
        "ok": 54,
        "ko": 0
    },
    "percentiles1": {
        "total": 152,
        "ok": 152,
        "ko": 0
    },
    "percentiles2": {
        "total": 156,
        "ok": 156,
        "ko": 0
    },
    "percentiles3": {
        "total": 250,
        "ok": 250,
        "ko": 0
    },
    "percentiles4": {
        "total": 333,
        "ok": 333,
        "ko": 0
    },
    "group1": {
    "name": "t < 800 ms",
    "count": 13,
    "percentage": 100
},
    "group2": {
    "name": "800 ms < t < 1200 ms",
    "count": 0,
    "percentage": 0
},
    "group3": {
    "name": "t > 1200 ms",
    "count": 0,
    "percentage": 0
},
    "group4": {
    "name": "failed",
    "count": 0,
    "percentage": 0
},
    "meanNumberOfRequestsPerSecond": {
        "total": 0.52,
        "ok": 0.52,
        "ko": 0
    }
}